{
    "qa_pairs": [
        {
            "question": "이번 학기 재학 중이신가요?",
            "answer": "네네, 여름학기 무료입니다."
        },
        {
            "question": "MATH2111 수강 신청 많이 빡셀까요?",
            "answer": "상당히 빡세보이네요."
        },
        {
            "question": "혹시 NOL 신청하는 방법 어디서 찾아야 하나요?",
            "answer": "원래 비자랑 같이 나오는 거라, 이민국에 문의 넣어보세요."
        },
        {
            "question": "과제 열심히 하고 중간기말 -1sd 정도 받으면 F는 안 뜨죠?",
            "answer": "F는 뜨기 어려운 점수여서 받으시면 자랑하셔도 되는 수준이에요."
        },
        {
            "question": "100점 만점에 몇이면 F인가요?",
            "answer": "0점입니다."
        },
        {
            "question": "혹시 졸업가운 같이 구매하실 분 있나요?",
            "answer": "M 사이즈입니다."
        },
        {
            "question": "여름에 한국에서 인턴 구할 때 보통 어디서들 구하시나요?",
            "answer": "공고나 지인에게서 구하죠."
        },
        {
            "question": "혹시 summer hall late application 받아준 케이스 있나요?",
            "answer": "셜로한테 이메일 보내시고 직접 방문도 하세요."
        },
        {
            "question": "군대 + 인턴 포함해서 총 2년반 휴학해도 학교에서 승인 해줄까요?",
            "answer": "병적 증명서 제출하고 어드바이저랑 잘 얘기하면 문제 없을 거예요."
        },
        {
            "question": "혹시 다음 학기 기숙사 배정 결과 언제 나오는지 아시는 분 있나요?",
            "answer": "5월 29일 날이라고 나와있네요."
        }
    ]
}