{
    "qa_pairs": [
        {
            "question": "오늘 LG1 학식 여나요?",
            "answer": "https://cso.ust.hk/special-opening-hours"
        },
        {
            "question": "현재 과기대에 재학중인상태인데, 전과/더블메이저를 하고싶은데 도저히 남은 학기 내로 다 수업을 들을수가 없어서 재입학도 고려중입니다. 재입학한 경우가 있었나요? 더블메이저 하다가 5학년까지 다니는 경우도 많이 있나요?",
            "answer": "재입학보다는 추가학기 다니는게 가능한지 일단 학과에 여쭤보시는게 낫지 않을까요; 4년동안 credit을 다 못채워서 5학년까지 다닌사람 봤어요."
        },
        {
            "question": "휴학생들은 당연히 수영장 못들어가겠죠?",
            "answer": "휴학생은 도서관도 안들여보내주던데요."
        },
        {
            "question": "계절 웨잇 잘 빠지나요?",
            "answer": "은근 잘빠져요."
        },
        {
            "question": "여름학기도 파이널시험 스케줄이 가을/봄학기처럼 학기 중에 나중에 나오나요? 아니면 예를 들어 8월 10일까지면 시험도 포함되는 건가요?",
            "answer": "답변 없음"
        }
    ]
}