{
    "qa_pairs": [
        {
            "question": "저희 학교 졸업식이 1년에 한번 연말에 하는건가요?",
            "answer": "연말에 다 몰아서 합니다."
        },
        {
            "question": "그럼 보통 봄학기 졸업자들은 졸업식 따로 없이 각자 사진찍고 끝나나요?",
            "answer": "답변 없음"
        },
        {
            "question": "혹시 비슷한 일을 겪으신 분이 계실까요?",
            "answer": "제 경험상 카드 정지하고 새로운 거 만드는 게 더 빨라요; 상상 이상으로 시간 걸립니다."
        },
        {
            "question": "한 달이면 괜찮을까요..?",
            "answer": "길어봐야 2주면 옵니다 보통."
        },
        {
            "question": "혹시 애플펜슬 팁 여분 가지고있는 분 계시나요?",
            "answer": "Tko에 팔아요."
        },
        {
            "question": "감사합니다! 그럼 졸업식 아예 참석 안하시는 분들도 많은가요?",
            "answer": "답변 없음"
        },
        {
            "question": "혹시 학교에서 출발하시면 저도 껴도 될까요?",
            "answer": "학교에서 출발해요!"
        },
        {
            "question": "혹시 도서관에 A4용지가 비치되어있는 곳이 있나요?",
            "answer": "프린터에서 빼쓰세요; 관리하시는 분들이 뭐라고 안 하시겠죠..?"
        },
        {
            "question": "저희 학기당 몇 장까지 무료로 프린트인가요?",
            "answer": "180인가 그럴거에요."
        },
        {
            "question": "학부 오피스 이메일 어디 있는지 아시는 분?",
            "answer": "학부 페이지에서 검색해보세요."
        }
    ]
}