{
    "qa_pairs": [
        {
            "question": "Application for Leave in the current term within two weeks prior to the commencement of the final examination period will normally not be accepted. 이 뜻은 만약 봄학기를 휴학하고 싶은 거면 데드라인이 봄학기 final examination commencement 전까지라는 거겠죠?",
            "answer": "이번학기 말하는걸꺼에요, 다음학기껀 add drop 전에만 내면 정상으로 될껍니다."
        },
        {
            "question": "기숙사 웨잇이 풀리면 기숙사 못받나요?",
            "answer": "웨잇 풀리면 메일 보내시면 돼요."
        },
        {
            "question": "혹시 기숙사 졸업생도 출입 가능한가요?",
            "answer": "네 날라가요."
        },
        {
            "question": "기숙사 늦게 신청해서 기숙사 받아보신분 계신가요?",
            "answer": "답변 없음"
        },
        {
            "question": "기숙사 방에 벌이 들어왔는데 어떡해야 하나요?",
            "answer": "벌이니까 달게 받으세요."
        },
        {
            "question": "저희 학교 클리닉 어디 있나요?",
            "answer": "미용실 있는 곳 아시나요? 그쪽으로 쭉 들어가면 있어요."
        },
        {
            "question": "혹시 학교에서 인터넷 제일 빠른 곳이 어디일까요?",
            "answer": "5홀이요; 근데 5홀 인터넷 진짜 상대적으로 빠르긴 해요; 과기대 최고의 기숙사죠."
        }
    ]
}