{
    "qa_pairs": [
        {
            "question": "30인데 가망있나요?",
            "answer": "가능"
        },
        {
            "question": "Huma 1000a 69번도 가망있나요?",
            "answer": "답변 없음"
        },
        {
            "question": "econ2103은 잘 빠지나요?",
            "answer": "답변 없음"
        },
        {
            "question": "혹시 sis에서 waitlist 번호 확인하는 방법 있나요?",
            "answer": "Sis에서는 enroll -> my class schedule로 가서 show waitlisted classes 필터 체크하고 확인하실 수 있고요; Usthing은 한번 새로고침 해보세요."
        },
        {
            "question": "제 현재 번호도 혹시 같이 뜨나요?",
            "answer": "네 같이 뜹니다."
        },
        {
            "question": "비자 만기 돼서, 다시 재신청할 때 필요한 서류 뭐뭐 있는지 아시는 분 계실까요?",
            "answer": "google"
        },
        {
            "question": "혹시 드라이기 어디서 사나요?",
            "answer": "전 tko 쇼핑몰 안 가전제품 상점에서 샀어요; Fortress 같은 가전제품 매장이나 Log on 같은 문구점에서도 팔아요; Jhc나 가전제품 파는 곳에서 팔아요."
        },
        {
            "question": "학생 옥토퍼스 신청하려고 하는데 school information에서 과기대가 없던데 혹시 방법 아시는 분 계실까요?",
            "answer": "답변 없음"
        },
        {
            "question": "혹시 2월 3일 아침 11시 20분 도착해서 택시 쉐어 하실 분 계신가요?",
            "answer": "답변 없음"
        },
        {
            "question": "내일(30일) 정오쯤 같이 택시 타실 분 있으실까요?",
            "answer": "답변 없음"
        },
        {
            "question": "혹시 홍콩 돌아가실 때 인천공항에 비행기 디파쳐 시간보다 얼마나 일찍 가셨나요?",
            "answer": "글쎄요…딜레이 된 적은 있어도…일찍 비행기가 뜬 적은 없었어요; 저는 3시간 먼저 갔습니다."
        },
        {
            "question": "혹시 몇 시 비행기셨나요? 그리고 3시간 정도면 충분하셨나요?",
            "answer": "짐 부치는데 40분, 보안 검색 한 시간 좀 넘게 걸렸습니다."
        },
        {
            "question": "홀1에 트롤리 있나요?",
            "answer": "G층에 있어요."
        }
    ]
}